cliargtools
