Metadata-Version: 2.1
Name: CliArgTools
Version: 1.2
Summary: Small and easy to use library for working with CLI arguments
Home-page: https://github.com/neongm/CliArgTools
Author: Vologin Alexander
Author-email: chura2013c@gmail.com
License: MIT
Keywords: cli arguments parsing parser command line
Platform: UNKNOWN
